Workbook

Sheet Inputs
A1: Escenario | B1: Factor demanda B2B | C1: Precio premium USD | D1: Eficiencia Green | E1: Factor SAF | F1: Descripción | H1: Parámetro | I1: Valor
A2: Base | B2: 1 | C2: 115 | D2: 0.12 | E2: 1 | F2: Piloto normal con adopción esperada y eficiencia operacional estándar. | H2: Ruta piloto | I2: Santiago - Miami
A3: Conservador | B3: 0.82 | C3: 105 | D3: 0.06 | E3: 1.04 | F3: Menor adopción corporativa y menor reducción de APU. | H3: Precio Jet Fuel USD/L | I3: 0.85
A4: Optimista | B4: 1.22 | C4: 130 | D4: 0.16 | E4: 0.97 | F4: Mayor adopción B2B, mejor disposición a pagar y eficiencia operacional. | H4: Precio SAF USD/L | I4: 3.4
A5: Crisis B2B | B5: 0.58 | C5: 95 | D5: 0.05 | E5: 1.06 | F5: Semana crítica con caída de ventas corporativas y presión competitiva. | H5: Sobrecosto SAF USD/L | I5: =I4-I3
A6: Eficiencia Green | B6: 0.96 | C6: 115 | D6: 0.24 | E6: 0.92 | F6: Foco en eficiencia de combustible, menor APU y uso optimizado de SAF. | H6: Meta cobertura SAF | I6: 1
H7: Meta APU minutos | I7: 9
H8: Meta asientos Eco-Corp por vuelo | I8: 20
H10: Nota litros SAF | I10: Litros SAF Base representa solo el 15% obligatorio de SAF por vuelo, no el consumo total de combustible.

Sheet Data_Dinamica
A1: Fecha | B1: Semana | C1: Mes | D1: N° Vuelo | E1: Ruta | F1: Asientos Base B2B | G1: Asientos Eco-Corp Dinámicos | H1: Precio Premium Dinámico | I1: Ingreso Premium USD | J1: Litros SAF Base | K1: Litros SAF Dinámicos | L1: Sobrecosto SAF USD | M1: APU Base Min | N1: APU Dinámico Min | O1: Adopción Protocolo Green | P1: Margen Neto USD | Q1: Semáforo B2B | R1: Minutos Retraso
A2: 46204 | B2: 1 | C2: Jul | D2: LA500 | E2: Santiago - Miami | F2: 18 | G2: =MAX(0,ROUND(F2*Dashboard!$H$5,0)) | H2: =Dashboard!$F$5 | I2: =G2*H2 | J2: 843 | K2: =J2*Dashboard!$L$5*(1-Dashboard!$J$5*0.35) | L2: =K2*Inputs!$I$5 | M2: 13.1 | N2: =M2*(1-Dashboard!$J$5) | O2: =IF(N2<=Inputs!$I$7,"Verde",IF(N2<=Inputs!$I$7+2,"Amarillo","Rojo")) | P2: =I2-L2 | Q2: =IF(G2>=Inputs!$I$8,"Verde",IF(G2>=Inputs!$I$8*0.85,"Amarillo","Rojo")) | R2: 8
A3: 46205 | B3: 1 | C3: Jul | D3: LA501 | E3: Santiago - Miami | F3: 18 | G3: =MAX(0,ROUND(F3*Dashboard!$H$5,0)) | H3: =Dashboard!$F$5 | I3: =G3*H3 | J3: 898 | K3: =J3*Dashboard!$L$5*(1-Dashboard!$J$5*0.35) | L3: =K3*Inputs!$I$5 | M3: 13.1 | N3: =M3*(1-Dashboard!$J$5) | O3: =IF(N3<=Inputs!$I$7,"Verde",IF(N3<=Inputs!$I$7+2,"Amarillo","Rojo")) | P3: =I3-L3 | Q3: =IF(G3>=Inputs!$I$8,"Verde",IF(G3>=Inputs!$I$8*0.85,"Amarillo","Rojo")) | R3: 11
A4: 46206 | B4: 1 | C4: Jul | D4: LA502 | E4: Santiago - Miami | F4: 25 | G4: =MAX(0,ROUND(F4*Dashboard!$H$5,0)) | H4: =Dashboard!$F$5 | I4: =G4*H4 | J4: 852 | K4: =J4*Dashboard!$L$5*(1-Dashboard!$J$5*0.35) | L4: =K4*Inputs!$I$5 | M4: 12.3 | N4: =M4*(1-Dashboard!$J$5) | O4: =IF(N4<=Inputs!$I$7,"Verde",IF(N4<=Inputs!$I$7+2,"Amarillo","Rojo")) | P4: =I4-L4 | Q4: =IF(G4>=Inputs!$I$8,"Verde",IF(G4>=Inputs!$I$8*0.85,"Amarillo","Rojo")) | R4: 10
A5: 46207 | B5: 1 | C5: Jul | D5: LA503 | E5: Santiago - Miami | F5: 20 | G5: =MAX(0,ROUND(F5*Dashboard!$H$5,0)) | H5: =Dashboard!$F$5 | I5: =G5*H5 | J5: 934 | K5: =J5*Dashboard!$L$5*(1-Dashboard!$J$5*0.35) | L5: =K5*Inputs!$I$5 | M5: 12.4 | N5: =M5*(1-Dashboard!$J$5) | O5: =IF(N5<=Inputs!$I$7,"Verde",IF(N5<=Inputs!$I$7+2,"Amarillo","Rojo")) | P5: =I5-L5 | Q5: =IF(G5>=Inputs!$I$8,"Verde",IF(G5>=Inputs!$I$8*0.85,"Amarillo","Rojo")) | R5: 8
A6: 46208 | B6: 1 | C6: Jul | D6: LA504 | E6: Santiago - Miami | F6: 25 | G6: =MAX(0,ROUND(F6*Dashboard!$H$5,0)) | H6: =Dashboard!$F$5 | I6: =G6*H6 | J6: 898 | K6: =J6*Dashboard!$L$5*(1-Dashboard!$J$5*0.35) | L6: =K6*Inputs!$I$5 | M6: 13 | N6: =M6*(1-Dashboard!$J$5) | O6: =IF(N6<=Inputs!$I$7,"Verde",IF(N6<=Inputs!$I$7+2,"Amarillo","Rojo")) | P6: =I6-L6 | Q6: =IF(G6>=Inputs!$I$8,"Verde",IF(G6>=Inputs!$I$8*0.85,"Amarillo","Rojo")) | R6: 6
A7: 46209 | B7: 1 | C7: Jul | D7: LA505 | E7: Santiago - Miami | F7: 24 | G7: =MAX(0,ROUND(F7*Dashboard!$H$5,0)) | H7: =Dashboard!$F$5 | I7: =G7*H7 | J7: 857 | K7: =J7*Dashboard!$L$5*(1-Dashboard!$J$5*0.35) | L7: =K7*Inputs!$I$5 | M7: 10.7 | N7: =M7*(1-Dashboard!$J$5) | O7: =IF(N7<=Inputs!$I$7,"Verde",IF(N7<=Inputs!$I$7+2,"Amarillo","Rojo")) | P7: =I7-L7 | Q7: =IF(G7>=Inputs!$I$8,"Verde",IF(G7>=Inputs!$I$8*0.85,"Amarillo","Rojo")) | R7: 2
A8: 46210 | B8: 1 | C8: Jul | D8: LA506 | E8: Santiago - Miami | F8: 17 | G8: =MAX(0,ROUND(F8*Dashboard!$H$5,0)) | H8: =Dashboard!$F$5 | I8: =G8*H8 | J8: 839 | K8: =J8*Dashboard!$L$5*(1-Dashboard!$J$5*0.35) | L8: =K8*Inputs!$I$5 | M8: 13.5 | N8: =M8*(1-Dashboard!$J$5) | O8: =IF(N8<=Inputs!$I$7,"Verde",IF(N8<=Inputs!$I$7+2,"Amarillo","Rojo")) | P8: =I8-L8 | Q8: =IF(G8>=Inputs!$I$8,"Verde",IF(G8>=Inputs!$I$8*0.85,"Amarillo","Rojo")) | R8: 6
A9: 46211 | B9: 2 | C9: Jul | D9: LA500 | E9: Santiago - Miami | F9: 19 | G9: =MAX(0,ROUND(F9*Dashboard!$H$5,0)) | H9: =Dashboard!$F$5 | I9: =G9*H9 | J9: 927 | K9: =J9*Dashboard!$L$5*(1-Dashboard!$J$5*0.35) | L9: =K9*Inputs!$I$5 | M9: 14.3 | N9: =M9*(1-Dashboard!$J$5) | O9: =IF(N9<=Inputs!$I$7,"Verde",IF(N9<=Inputs!$I$7+2,"Amarillo","Rojo")) | P9: =I9-L9 | Q9: =IF(G9>=Inputs!$I$8,"Verde",IF(G9>=Inputs!$I$8*0.85,"Amarillo","Rojo")) | R9: 2
A10: 46212 | B10: 2 | C10: Jul | D10: LA501 | E10: Santiago - Miami | F10: 22 | G10: =MAX(0,ROUND(F10*Dashboard!$H$5,0)) | H10: =Dashboard!$F$5 | I10: =G10*H10 | J10: 915 | K10: =J10*Dashboard!$L$5*(1-Dashboard!$J$5*0.35) | L10: =K10*Inputs!$I$5 | M10: 9.7 | N10: =M10*(1-Dashboard!$J$5) | O10: =IF(N10<=Inputs!$I$7,"Verde",IF(N10<=Inputs!$I$7+2,"Amarillo","Rojo")) | P10: =I10-L10 | Q10: =IF(G10>=Inputs!$I$8,"Verde",IF(G10>=Inputs!$I$8*0.85,"Amarillo","Rojo")) | R10: 17
A11: 46213 | B11: 2 | C11: Jul | D11: LA502 | E11: Santiago - Miami | F11: 21 | G11: =MAX(0,ROUND(F11*Dashboard!$H$5,0)) | H11: =Dashboard!$F$5 | I11: =G11*H11 | J11: 917 | K11: =J11*Dashboard!$L$5*(1-Dashboard!$J$5*0.35) | L11: =K11*Inputs!$I$5 | M11: 13.1 | N11: =M11*(1-Dashboard!$J$5) | O11: =IF(N11<=Inputs!$I$7,"Verde",IF(N11<=Inputs!$I$7+2,"Amarillo","Rojo")) | P11: =I11-L11 | Q11: =IF(G11>=Inputs!$I$8,"Verde",IF(G11>=Inputs!$I$8*0.85,"Amarillo","Rojo")) | R11: 14
A12: 46214 | B12: 2 | C12: Jul | D12: LA503 | E12: Santiago - Miami | F12: 25 | G12: =MAX(0,ROUND(F12*Dashboard!$H$5,0)) | H12: =Dashboard!$F$5 | I12: =G12*H12 | J12: 843 | K12: =J12*Dashboard!$L$5*(1-Dashboard!$J$5*0.35) | L12: =K12*Inputs!$I$5 | M12: 14.4 | N12: =M12*(1-Dashboard!$J$5) | O12: =IF(N12<=Inputs!$I$7,"Verde",IF(N12<=Inputs!$I$7+2,"Amarillo","Rojo")) | P12: =I12-L12 | Q12: =IF(G12>=Inputs!$I$8,"Verde",IF(G12>=Inputs!$I$8*0.85,"Amarillo","Rojo")) | R12: 2
A13: 46215 | B13: 2 | C13: Jul | D13: LA504 | E13: Santiago - Miami | F13: 22 | G13: =MAX(0,ROUND(F13*Dashboard!$H$5,0)) | H13: =Dashboard!$F$5 | I13: =G13*H13 | J13: 870 | K13: =J13*Dashboard!$L$5*(1-Dashboard!$J$5*0.35) | L13: =K13*Inputs!$I$5 | M13: 10.2 | N13: =M13*(1-Dashboard!$J$5) | O13: =IF(N13<=Inputs!$I$7,"Verde",IF(N13<=Inputs!$I$7+2,"Amarillo","Rojo")) | P13: =I13-L13 | Q13: =IF(G13>=Inputs!$I$8,"Verde",IF(G13>=Inputs!$I$8*0.85,"Amarillo","Rojo")) | R13: 13
... A61: 46263 | B61: 9 | C61: Aug | D61: LA503 | E61: Santiago - Miami | F61: 19 | G61: =MAX(0,ROUND(F61*Dashboard!$H$5,0)) | H61: =Dashboard!$F$5 | I61: =G61*H61 | J61: 946 | K61: =J61*Dashboard!$L$5*(1-Dashboard!$J$5*0.35) | L61: =K61*Inputs!$I$5 | M61: 12.4 | N61: =M61*(1-Dashboard!$J$5) | O61: =IF(N61<=Inputs!$I$7,"Verde",IF(N61<=Inputs!$I$7+2,"Amarillo","Rojo")) | P61: =I61-L61 | Q61: =IF(G61>=Inputs!$I$8,"Verde",IF(G61>=Inputs!$I$8*0.85,"Amarillo","Rojo")) | R61: 7

Sheet Calculos
A1: Semana | B1: Asientos Eco-Corp | C1: Ingreso Premium | D1: Sobrecosto SAF | E1: Cobertura SAF | F1: APU Promedio | G1: Margen Neto | I1: Escenario | J1: Asientos | K1: Ingreso Premium | L1: Sobrecosto SAF | M1: Cobertura | N1: Margen Neto
A2: 1 | B2: =SUMIFS(Data_Dinamica!$G$2:$G$61,Data_Dinamica!$B$2:$B$61,A2) | C2: =SUMIFS(Data_Dinamica!$I$2:$I$61,Data_Dinamica!$B$2:$B$61,A2) | D2: =SUMIFS(Data_Dinamica!$L$2:$L$61,Data_Dinamica!$B$2:$B$61,A2) | E2: =IF(D2=0,0,C2/D2) | F2: =IFERROR(AVERAGEIFS(Data_Dinamica!$N$2:$N$61,Data_Dinamica!$B$2:$B$61,A2),0) | G2: =C2-D2 | I2: Base | J2: =ROUND(SUM(Data_Dinamica!$F$2:$F$61)*INDEX(Inputs!$B$2:$B$6,MATCH(I2,Inputs!$A$2:$A$6,0)),0) | K2: =J2*INDEX(Inputs!$C$2:$C$6,MATCH(I2,Inputs!$A$2:$A$6,0)) | L2: =SUM(Data_Dinamica!$J$2:$J$61)*INDEX(Inputs!$E$2:$E$6,MATCH(I2,Inputs!$A$2:$A$6,0))*(1-INDEX(Inputs!$D$2:$D$6,MATCH(I2,Inputs!$A$2:$A$6,0))*0.35)*Inputs!$I$5 | M2: =IF(L2=0,0,K2/L2) | N2: =K2-L2
A3: 2 | B3: =SUMIFS(Data_Dinamica!$G$2:$G$61,Data_Dinamica!$B$2:$B$61,A3) | C3: =SUMIFS(Data_Dinamica!$I$2:$I$61,Data_Dinamica!$B$2:$B$61,A3) | D3: =SUMIFS(Data_Dinamica!$L$2:$L$61,Data_Dinamica!$B$2:$B$61,A3) | E3: =IF(D3=0,0,C3/D3) | F3: =IFERROR(AVERAGEIFS(Data_Dinamica!$N$2:$N$61,Data_Dinamica!$B$2:$B$61,A3),0) | G3: =C3-D3 | I3: Conservador | J3: =ROUND(SUM(Data_Dinamica!$F$2:$F$61)*INDEX(Inputs!$B$2:$B$6,MATCH(I3,Inputs!$A$2:$A$6,0)),0) | K3: =J3*INDEX(Inputs!$C$2:$C$6,MATCH(I3,Inputs!$A$2:$A$6,0)) | L3: =SUM(Data_Dinamica!$J$2:$J$61)*INDEX(Inputs!$E$2:$E$6,MATCH(I3,Inputs!$A$2:$A$6,0))*(1-INDEX(Inputs!$D$2:$D$6,MATCH(I3,Inputs!$A$2:$A$6,0))*0.35)*Inputs!$I$5 | M3: =IF(L3=0,0,K3/L3) | N3: =K3-L3
A4: 3 | B4: =SUMIFS(Data_Dinamica!$G$2:$G$61,Data_Dinamica!$B$2:$B$61,A4) | C4: =SUMIFS(Data_Dinamica!$I$2:$I$61,Data_Dinamica!$B$2:$B$61,A4) | D4: =SUMIFS(Data_Dinamica!$L$2:$L$61,Data_Dinamica!$B$2:$B$61,A4) | E4: =IF(D4=0,0,C4/D4) | F4: =IFERROR(AVERAGEIFS(Data_Dinamica!$N$2:$N$61,Data_Dinamica!$B$2:$B$61,A4),0) | G4: =C4-D4 | I4: Optimista | J4: =ROUND(SUM(Data_Dinamica!$F$2:$F$61)*INDEX(Inputs!$B$2:$B$6,MATCH(I4,Inputs!$A$2:$A$6,0)),0) | K4: =J4*INDEX(Inputs!$C$2:$C$6,MATCH(I4,Inputs!$A$2:$A$6,0)) | L4: =SUM(Data_Dinamica!$J$2:$J$61)*INDEX(Inputs!$E$2:$E$6,MATCH(I4,Inputs!$A$2:$A$6,0))*(1-INDEX(Inputs!$D$2:$D$6,MATCH(I4,Inputs!$A$2:$A$6,0))*0.35)*Inputs!$I$5 | M4: =IF(L4=0,0,K4/L4) | N4: =K4-L4
A5: 4 | B5: =SUMIFS(Data_Dinamica!$G$2:$G$61,Data_Dinamica!$B$2:$B$61,A5) | C5: =SUMIFS(Data_Dinamica!$I$2:$I$61,Data_Dinamica!$B$2:$B$61,A5) | D5: =SUMIFS(Data_Dinamica!$L$2:$L$61,Data_Dinamica!$B$2:$B$61,A5) | E5: =IF(D5=0,0,C5/D5) | F5: =IFERROR(AVERAGEIFS(Data_Dinamica!$N$2:$N$61,Data_Dinamica!$B$2:$B$61,A5),0) | G5: =C5-D5 | I5: Crisis B2B | J5: =ROUND(SUM(Data_Dinamica!$F$2:$F$61)*INDEX(Inputs!$B$2:$B$6,MATCH(I5,Inputs!$A$2:$A$6,0)),0) | K5: =J5*INDEX(Inputs!$C$2:$C$6,MATCH(I5,Inputs!$A$2:$A$6,0)) | L5: =SUM(Data_Dinamica!$J$2:$J$61)*INDEX(Inputs!$E$2:$E$6,MATCH(I5,Inputs!$A$2:$A$6,0))*(1-INDEX(Inputs!$D$2:$D$6,MATCH(I5,Inputs!$A$2:$A$6,0))*0.35)*Inputs!$I$5 | M5: =IF(L5=0,0,K5/L5) | N5: =K5-L5
A6: 5 | B6: =SUMIFS(Data_Dinamica!$G$2:$G$61,Data_Dinamica!$B$2:$B$61,A6) | C6: =SUMIFS(Data_Dinamica!$I$2:$I$61,Data_Dinamica!$B$2:$B$61,A6) | D6: =SUMIFS(Data_Dinamica!$L$2:$L$61,Data_Dinamica!$B$2:$B$61,A6) | E6: =IF(D6=0,0,C6/D6) | F6: =IFERROR(AVERAGEIFS(Data_Dinamica!$N$2:$N$61,Data_Dinamica!$B$2:$B$61,A6),0) | G6: =C6-D6 | I6: Eficiencia Green | J6: =ROUND(SUM(Data_Dinamica!$F$2:$F$61)*INDEX(Inputs!$B$2:$B$6,MATCH(I6,Inputs!$A$2:$A$6,0)),0) | K6: =J6*INDEX(Inputs!$C$2:$C$6,MATCH(I6,Inputs!$A$2:$A$6,0)) | L6: =SUM(Data_Dinamica!$J$2:$J$61)*INDEX(Inputs!$E$2:$E$6,MATCH(I6,Inputs!$A$2:$A$6,0))*(1-INDEX(Inputs!$D$2:$D$6,MATCH(I6,Inputs!$A$2:$A$6,0))*0.35)*Inputs!$I$5 | M6: =IF(L6=0,0,K6/L6) | N6: =K6-L6
A7: 6 | B7: =SUMIFS(Data_Dinamica!$G$2:$G$61,Data_Dinamica!$B$2:$B$61,A7) | C7: =SUMIFS(Data_Dinamica!$I$2:$I$61,Data_Dinamica!$B$2:$B$61,A7) | D7: =SUMIFS(Data_Dinamica!$L$2:$L$61,Data_Dinamica!$B$2:$B$61,A7) | E7: =IF(D7=0,0,C7/D7) | F7: =IFERROR(AVERAGEIFS(Data_Dinamica!$N$2:$N$61,Data_Dinamica!$B$2:$B$61,A7),0) | G7: =C7-D7
A8: 7 | B8: =SUMIFS(Data_Dinamica!$G$2:$G$61,Data_Dinamica!$B$2:$B$61,A8) | C8: =SUMIFS(Data_Dinamica!$I$2:$I$61,Data_Dinamica!$B$2:$B$61,A8) | D8: =SUMIFS(Data_Dinamica!$L$2:$L$61,Data_Dinamica!$B$2:$B$61,A8) | E8: =IF(D8=0,0,C8/D8) | F8: =IFERROR(AVERAGEIFS(Data_Dinamica!$N$2:$N$61,Data_Dinamica!$B$2:$B$61,A8),0) | G8: =C8-D8
A9: 8 | B9: =SUMIFS(Data_Dinamica!$G$2:$G$61,Data_Dinamica!$B$2:$B$61,A9) | C9: =SUMIFS(Data_Dinamica!$I$2:$I$61,Data_Dinamica!$B$2:$B$61,A9) | D9: =SUMIFS(Data_Dinamica!$L$2:$L$61,Data_Dinamica!$B$2:$B$61,A9) | E9: =IF(D9=0,0,C9/D9) | F9: =IFERROR(AVERAGEIFS(Data_Dinamica!$N$2:$N$61,Data_Dinamica!$B$2:$B$61,A9),0) | G9: =C9-D9
A10: 9 | B10: =SUMIFS(Data_Dinamica!$G$2:$G$61,Data_Dinamica!$B$2:$B$61,A10) | C10: =SUMIFS(Data_Dinamica!$I$2:$I$61,Data_Dinamica!$B$2:$B$61,A10) | D10: =SUMIFS(Data_Dinamica!$L$2:$L$61,Data_Dinamica!$B$2:$B$61,A10) | E10: =IF(D10=0,0,C10/D10) | F10: =IFERROR(AVERAGEIFS(Data_Dinamica!$N$2:$N$61,Data_Dinamica!$B$2:$B$61,A10),0) | G10: =C10-D10

Sheet Dashboard
A1: LATAM Eco-Corporate Premium | Dashboard interactivo BSC
A2: Ruta piloto: Santiago - Miami. Modelo para cubrir el sobrecosto SAF obligatorio con sobreprecio B2B y certificados Scope 3, manteniendo competitividad frente a Ultra-Low-Cost.
A5: Semana | B5: 3 | C5: Escenario | D5: Base | E5: Precio Premium | F5: =VLOOKUP($D$5,Inputs!$A$2:$E$6,3,FALSE) | G5: Factor Adopción | H5: =VLOOKUP($D$5,Inputs!$A$2:$E$6,2,FALSE) | I5: Eficiencia Green | J5: =VLOOKUP($D$5,Inputs!$A$2:$E$6,4,FALSE) | K5: Factor SAF | L5: =VLOOKUP($D$5,Inputs!$A$2:$E$6,5,FALSE) | M5: Estado | N5: =IF($A$14<Inputs!$I$8*IF($B$5="Todos",60,7)*0.85,"CRISIS","OK")
A7: SLICER ESCENARIO | H7: SLICER SEMANA
A8: Base | B8: Conservador | C8: Optimista | D8: Crisis B2B | E8: Eficiencia Green | H8: Todos | I8: 1 | J8: 2 | K8: 3 | L8: 4 | M8: 5 | N8: 6
A9: =IF($D$5=A8,"● seleccionado","○") | B9: =IF($D$5=B8,"● seleccionado","○") | C9: =IF($D$5=C8,"● seleccionado","○") | D9: =IF($D$5=D8,"● seleccionado","○") | E9: =IF($D$5=E8,"● seleccionado","○") | H9: =IF($B$5=H8,"●","○") | I9: =IF($B$5=I8,"●","○") | J9: =IF($B$5=J8,"●","○") | K9: =IF($B$5=K8,"●","○") | L9: =IF($B$5=L8,"●","○") | M9: =IF($B$5=M8,"●","○") | N9: =IF($B$5=N8,"●","○")
H10: 7 | I10: 8 | J10: 9
H11: =IF($B$5=H10,"●","○") | I11: =IF($B$5=I10,"●","○") | J11: =IF($B$5=J10,"●","○")
A13: Asientos vendidos | C13: Ingreso premium | E13: Sobrecosto SAF | G13: Cobertura SAF | I13: Margen neto | K13: APU promedio | M13: Adopción Green
A14: =IF($B$5="Todos",SUM(Data_Dinamica!$G$2:$G$61),SUMIF(Data_Dinamica!$B$2:$B$61,$B$5,Data_Dinamica!$G$2:$G$61)) | C14: =IF($B$5="Todos",SUM(Data_Dinamica!$I$2:$I$61),SUMIF(Data_Dinamica!$B$2:$B$61,$B$5,Data_Dinamica!$I$2:$I$61)) | E14: =IF($B$5="Todos",SUM(Data_Dinamica!$L$2:$L$61),SUMIF(Data_Dinamica!$B$2:$B$61,$B$5,Data_Dinamica!$L$2:$L$61)) | G14: =IFERROR(C14/E14,0) | I14: =C14-E14 | K14: =IF($B$5="Todos",AVERAGE(Data_Dinamica!$N$2:$N$61),AVERAGEIF(Data_Dinamica!$B$2:$B$61,$B$5,Data_Dinamica!$N$2:$N$61)) | M14: =COUNTIF(Data_Dinamica!$O$2:$O$61,"Verde")/COUNTA(Data_Dinamica!$O$2:$O$61)
A15: =IF(A14<Inputs!$I$8*IF($B$5="Todos",60,7)*0.85,"🔴 Rojo",IF(A14<Inputs!$I$8*IF($B$5="Todos",60,7),"🟡 Amarillo","🟢 Verde")) | C15: =IF(C14>=E14,"🟢 Cubre SAF","🔴 No cubre") | E15: =IF(E14<=C14,"🟢 Cubierto","🔴 Expuesto") | G15: =TEXT(G14,"0%")&" cobertura" | I15: =IF(I14>=0,"🟢 Margen positivo","🔴 Margen negativo") | K15: =IF(K14<=Inputs!$I$7,"🟢 Óptimo",IF(K14<=Inputs!$I$7+2,"🟡 Revisar APU","🔴 Crítico")) | M15: =IF(M14>=0.55,"🟢 Cultura en adopción","🟡 Reforzar protocolo")
A18: Gauge chart manual: eficiencia APU (Lead Measure) | H18: Resolución ágil en vivo: crisis semáforo rojo B2B
A19: Rojo | B19: >11 min | C19: Amarillo | D19: 9 a 11 min | E19: Verde | F19: ≤9 min | H19: Si semana 3 queda en rojo: en 48 horas el Squad comercial contacta top 10 cuentas corporativas, ofrece upgrade Eco-Corporate de prueba, activa certificado Scope 3 express, reasigna cupos desde business estándar y revisa pricing táctico para cerrar compromisos antes del siguiente ciclo de vuelos.
A20: ▇ | B20: ▇ | C20: ▇ | D20: ▇ | E20: ▇ | F20: ▇
A21: =IF($K$14>12,"▲","") | B21: =IF(AND($K$14>11,$K$14<=12),"▲","") | C21: =IF(AND($K$14>10,$K$14<=11),"▲","") | D21: =IF(AND($K$14>9,$K$14<=10),"▲","") | E21: =IF(AND($K$14>8,$K$14<=9),"▲","") | F21: =IF($K$14<=8,"▲","")
A22: ="APU promedio seleccionado: "&TEXT($K$14,"0.0")&" min | Meta ≤ "&Inputs!$I$7&" min"
A25: Resultado semanal dinámico | H25: Comparador de escenarios
A26: Semana | B26: Asientos | C26: Ingreso | D26: Sobrecosto | E26: Cobertura | F26: Margen | H26: Escenario | I26: Asientos | J26: Ingreso | K26: Sobrecosto | L26: Cobertura | M26: Margen
A27: 1 | B27: =SUMIF(Data_Dinamica!$B$2:$B$61,A27,Data_Dinamica!$G$2:$G$61) | C27: =SUMIF(Data_Dinamica!$B$2:$B$61,A27,Data_Dinamica!$I$2:$I$61) | D27: =SUMIF(Data_Dinamica!$B$2:$B$61,A27,Data_Dinamica!$L$2:$L$61) | E27: =IFERROR(C27/D27,0) | F27: =C27-D27 | H27: Base | I27: =Calculos!J2 | J27: =Calculos!K2 | K27: =Calculos!L2 | L27: =Calculos!M2 | M27: =Calculos!N2
A28: 2 | B28: =SUMIF(Data_Dinamica!$B$2:$B$61,A28,Data_Dinamica!$G$2:$G$61) | C28: =SUMIF(Data_Dinamica!$B$2:$B$61,A28,Data_Dinamica!$I$2:$I$61) | D28: =SUMIF(Data_Dinamica!$B$2:$B$61,A28,Data_Dinamica!$L$2:$L$61) | E28: =IFERROR(C28/D28,0) | F28: =C28-D28 | H28: Conservador | I28: =Calculos!J3 | J28: =Calculos!K3 | K28: =Calculos!L3 | L28: =Calculos!M3 | M28: =Calculos!N3
A29: 3 | B29: =SUMIF(Data_Dinamica!$B$2:$B$61,A29,Data_Dinamica!$G$2:$G$61) | C29: =SUMIF(Data_Dinamica!$B$2:$B$61,A29,Data_Dinamica!$I$2:$I$61) | D29: =SUMIF(Data_Dinamica!$B$2:$B$61,A29,Data_Dinamica!$L$2:$L$61) | E29: =IFERROR(C29/D29,0) | F29: =C29-D29 | H29: Optimista | I29: =Calculos!J4 | J29: =Calculos!K4 | K29: =Calculos!L4 | L29: =Calculos!M4 | M29: =Calculos!N4
A30: 4 | B30: =SUMIF(Data_Dinamica!$B$2:$B$61,A30,Data_Dinamica!$G$2:$G$61) | C30: =SUMIF(Data_Dinamica!$B$2:$B$61,A30,Data_Dinamica!$I$2:$I$61) | D30: =SUMIF(Data_Dinamica!$B$2:$B$61,A30,Data_Dinamica!$L$2:$L$61) | E30: =IFERROR(C30/D30,0) | F30: =C30-D30 | H30: Crisis B2B | I30: =Calculos!J5 | J30: =Calculos!K5 | K30: =Calculos!L5 | L30: =Calculos!M5 | M30: =Calculos!N5
A31: 5 | B31: =SUMIF(Data_Dinamica!$B$2:$B$61,A31,Data_Dinamica!$G$2:$G$61) | C31: =SUMIF(Data_Dinamica!$B$2:$B$61,A31,Data_Dinamica!$I$2:$I$61) | D31: =SUMIF(Data_Dinamica!$B$2:$B$61,A31,Data_Dinamica!$L$2:$L$61) | E31: =IFERROR(C31/D31,0) | F31: =C31-D31 | H31: Eficiencia Green | I31: =Calculos!J6 | J31: =Calculos!K6 | K31: =Calculos!L6 | L31: =Calculos!M6 | M31: =Calculos!N6
A32: 6 | B32: =SUMIF(Data_Dinamica!$B$2:$B$61,A32,Data_Dinamica!$G$2:$G$61) | C32: =SUMIF(Data_Dinamica!$B$2:$B$61,A32,Data_Dinamica!$I$2:$I$61) | D32: =SUMIF(Data_Dinamica!$B$2:$B$61,A32,Data_Dinamica!$L$2:$L$61) | E32: =IFERROR(C32/D32,0) | F32: =C32-D32
A33: 7 | B33: =SUMIF(Data_Dinamica!$B$2:$B$61,A33,Data_Dinamica!$G$2:$G$61) | C33: =SUMIF(Data_Dinamica!$B$2:$B$61,A33,Data_Dinamica!$I$2:$I$61) | D33: =SUMIF(Data_Dinamica!$B$2:$B$61,A33,Data_Dinamica!$L$2:$L$61) | E33: =IFERROR(C33/D33,0) | F33: =C33-D33
A34: 8 | B34: =SUMIF(Data_Dinamica!$B$2:$B$61,A34,Data_Dinamica!$G$2:$G$61) | C34: =SUMIF(Data_Dinamica!$B$2:$B$61,A34,Data_Dinamica!$I$2:$I$61) | D34: =SUMIF(Data_Dinamica!$B$2:$B$61,A34,Data_Dinamica!$L$2:$L$61) | E34: =IFERROR(C34/D34,0) | F34: =C34-D34
A35: 9 | B35: =SUMIF(Data_Dinamica!$B$2:$B$61,A35,Data_Dinamica!$G$2:$G$61) | C35: =SUMIF(Data_Dinamica!$B$2:$B$61,A35,Data_Dinamica!$I$2:$I$61) | D35: =SUMIF(Data_Dinamica!$B$2:$B$61,A35,Data_Dinamica!$L$2:$L$61) | E35: =IFERROR(C35/D35,0) | F35: =C35-D35

Sheet Instrucciones
A1: Cómo usar el dashboard interactivo LATAM
A2: 1 | B2: Abrir hoja Dashboard y usar los controles azules: Semana y Escenario.
A3: 2 | B3: El panel tiene segmentadores visuales tipo slicer; los botones muestran qué filtro está activo.
A4: 3 | B4: El gauge manual evalúa APU promedio: rojo >11 min, amarillo 9-11 min, verde ≤9 min.
A5: 4 | B5: Los KPIs se recalculan con el escenario elegido y muestran semáforo automático.
A6: 5 | B6: La hoja Data_Dinamica contiene 60 filas de vuelos simulados para la ruta Santiago - Miami.
A7: 6 | B7: La hoja Calculos resume semanas y escenarios para sostener el pitch y el comparador.
A8: 7 | B8: Para la crisis de semana 3: usar el bloque de acción ágil de 48 horas del Dashboard.
A9: 8 | B9: Para cambiar supuestos base, editar Inputs: precio premium, adopción B2B, eficiencia Green y factor SAF.
A10: 9 | B10: Elementos exigidos por pauta: data cruda 60 filas, cálculos dinámicos, slicer visual, gauge manual y semáforos.
